bone_models/__init__.py
bone_models/load_cases/__init__.py
bone_models/load_cases/lemaire_load_cases.py
bone_models/load_cases/lerebours_load_cases.py
bone_models/load_cases/martinez_reina_load_cases.py
bone_models/load_cases/martonova_load_cases.py
bone_models/load_cases/modiz_load_cases.py
bone_models/load_cases/pivonka_load_cases.py
bone_models/load_cases/scheiner_load_cases.py
bone_models/models/__init__.py
bone_models/models/base_model.py
bone_models/models/lemaire_model.py
bone_models/models/lerebours_model.py
bone_models/models/martinez_reina_model.py
bone_models/models/martonova_model.py
bone_models/models/modiz_model.py
bone_models/models/pivonka_model.py
bone_models/models/scheiner_model.py
bone_models/models/trichilo_model.py
bone_models/parameters/__init__.py
bone_models/parameters/base_parameters.py
bone_models/parameters/lemaire_parameters.py
bone_models/parameters/lerebours_parameters.py
bone_models/parameters/martinez_reina_parameters.py
bone_models/parameters/martonova_parameters.py
bone_models/parameters/modiz_parameters.py
bone_models/parameters/pivonka_parameters.py
bone_models/parameters/scheiner_parameters.py
bone_models/utils/__init__.py
bone_models/utils/plots.py
bone_models-0.1.0.dist-info/LICENSE
bone_models-0.1.0.dist-info/METADATA
bone_models-0.1.0.dist-info/WHEEL
bone_models-0.1.0.dist-info/top_level.txt
bone_models-0.1.0.dist-info/RECORD
