Metadata-Version: 2.2
Name: bone_models
Version: 0.1.0
Summary: A library for bone models including bone cell population, mineralization, and failure simulation models.
Author-email: Corinna Modiz <corinna.modiz@hdr.qut.edu.au>
License: MIT
Project-URL: homepage, https://github.com/cmodiz/Bone-Models
Project-URL: repository, https://github.com/cmodiz/Bone-Models
License-File: LICENSE
Requires-Dist: numpy
Requires-Dist: scipy
Requires-Dist: matplotlib
